{
  "metadata" : {
    "realm" : "/",
    "amsterVersion" : "5.5.1",
    "entityType" : "Policies",
    "entityId" : "ownPolicy",
    "pathParams" : { }
  },
  "data" : {
    "_id" : "ownPolicy",
    "name" : "ownPolicy",
    "active" : true,
    "description" : "",
    "resources" : [ "*://*:*/openidm/policy/managed/user/*" ],
    "actionValues" : {
      "GET" : true
    },
    "applicationName" : "openidm",
    "subject" : {
      "type" : "AuthenticatedUsers"
    },
    "condition" : {
      "type" : "Script",
      "scriptId" : "89658afd-7f74-49e6-bce7-8b0e5d2b35d1"
    },
    "resourceTypeUuid" : "76656a38-5f8e-401b-83aa-4ccb74ce88d2",
    "lastModifiedBy" : "id=amadmin,ou=user,dc=example,dc=com",
    "lastModifiedDate" : "2017-12-08T20:56:56.370Z",
    "createdBy" : "id=amadmin,ou=user,dc=example,dc=com",
    "creationDate" : "2017-12-08T20:56:56.370Z"
  }
}
