{
  "metadata" : {
    "realm" : "/",
    "entityType" : "ValidatedPasswordNode",
    "entityId" : "default/21a99653-a7a7-47ee-b650-f493a84bba09",
    "uid" : "ou=21a99653-a7a7-47ee-b650-f493a84bba09,ou=default,ou=OrganizationConfig,ou=1.0,ou=ValidatedPasswordNode,ou=services,ou=am-config",
    "sunServiceID" : "instance",
    "objectClass" : [ "top", "sunServiceComponent" ],
    "pathParams" : { },
    "ou" : null
  },
  "data" : {
    "validateInput" : true,
    "_type" : {
      "_id" : "ValidatedPasswordNode",
      "name" : "ValidatedPasswordNode",
      "collection" : false
    },
    "passwordAttribute" : "password",
    "_id" : "default/21a99653-a7a7-47ee-b650-f493a84bba09"
  }
}
